Workbook

Sheet Read Me
A1: The Crepes & Waffles Bar — Catering Economics Model
A2: Built for the Catering & Cakes launch. All blue cells with yellow fill are placeholders — replace with your real numbers.
A5: How to use this workbook
A6: 1. Go to the Assumptions tab. Every yellow/blue cell is a placeholder guess (typical dessert-catering ranges) — overwrite with your chef's real food cost, packaging cost and labor rate.
A7: 2. Go to the Unit Economics tab. Set your real retail prices in the blue Price cells — everything else recalculates.
A8: 3. Go to the Monthly P&L tab to see profit and the 50/50 partner split at 10 / 25 / 50 orders per month, and whether ad spend is covered at each volume.
A10: Color key
A11: Blue text on yellow fill = input — edit this
A12: Black text = formula — do not overwrite, it recalculates automatically
A13: Green text = pulled from another tab
A15: Every placeholder number is a typical industry range for a Miami dessert-catering operation, not your actual cost structure. Replace them before trusting the P&L tab.

Sheet Assumptions
A1: Assumptions
A2: Edit the blue/yellow Value cells with real numbers from you and the chef. Everything else in this workbook reads from here.
A4: Assumption | B4: Value | C4: Notes / Source
A5: Target food cost % | B5: 0.28 | C5: Typical dessert-catering range 25-30% of price. PLACEHOLDER — confirm with chef's actual recipe costing.
A6: Packaging cost — Canape Tray (24pc) | B6: 3 | C6: PLACEHOLDER — box, liners, labels
A7: Packaging cost — Canape Tray (36pc) | B7: 4 | C7: PLACEHOLDER
A8: Packaging cost — Canape Tray (48pc) | B8: 5 | C8: PLACEHOLDER
A9: Packaging cost — Cake (standard size) | B9: 4 | C9: PLACEHOLDER — cake box + board
A10: Production labor rate ($/hr) | B10: 22 | C10: PLACEHOLDER — chef/kitchen labor cost
A11: Labor hours — Canape Tray (24pc) | B11: 1 | C11: PLACEHOLDER — prep + assembly + plating
A12: Labor hours — Canape Tray (36pc) | B12: 1.4 | C12: PLACEHOLDER
A13: Labor hours — Canape Tray (48pc) | B13: 1.8 | C13: PLACEHOLDER
A14: Labor hours — Cake (standard size) | B14: 1.5 | C14: PLACEHOLDER
A15: Delivery cost per order | B15: 15 | C15: PLACEHOLDER — driver/gas/platform fee; $0 if pickup-only
A16: Payment processing fee % | B16: 0.03 | C16: Typical card processing 2.9-3.5%
... A22: Profit split — Chef % | B22: 0.5 | C22: Per crepes-waffles-catering-partnership-terms.md

Sheet Unit Economics
A1: Unit Economics — per product
A2: Set your real Price in the blue column. Everything else recalculates from Assumptions.
A4: Product | B4: Price | C4: Food Cost $ | D4: Packaging $ | E4: Labor $ | F4: Delivery $ | G4: Processing Fee $ | H4: Discount Allowance $ | I4: Total Variable Cost $ | J4: Gross Profit $ | K4: Gross Margin %
A5: Canape Tray — 24pc | B5: 150 | C5: =B5*Assumptions!$B$5 -> 42 | D5: =Assumptions!$B$6 -> 3 | E5: =Assumptions!$B$11*Assumptions!$B$10 -> 22 | F5: =Assumptions!$B$15 -> 15 | G5: =B5*Assumptions!$B$16 -> 4.5 | H5: =B5*Assumptions!$B$17 -> 1.5 | I5: =SUM(C5:H5) -> 88 | J5: =B5-I5 -> 62 | K5: =IFERROR(J5/B5,0) -> 0.41333333
A6: Canape Tray — 36pc | B6: 210 | C6: =B6*Assumptions!$B$5 -> 58.8 | D6: =Assumptions!$B$7 -> 4 | E6: =Assumptions!$B$12*Assumptions!$B$10 -> 30.8 | F6: =Assumptions!$B$15 -> 15 | G6: =B6*Assumptions!$B$16 -> 6.3 | H6: =B6*Assumptions!$B$17 -> 2.1 | I6: =SUM(C6:H6) -> 117 | J6: =B6-I6 -> 93 | K6: =IFERROR(J6/B6,0) -> 0.44285714
A7: Canape Tray — 48pc | B7: 270 | C7: =B7*Assumptions!$B$5 -> 75.6 | D7: =Assumptions!$B$8 -> 5 | E7: =Assumptions!$B$13*Assumptions!$B$10 -> 39.6 | F7: =Assumptions!$B$15 -> 15 | G7: =B7*Assumptions!$B$16 -> 8.1 | H7: =B7*Assumptions!$B$17 -> 2.7 | I7: =SUM(C7:H7) -> 146 | J7: =B7-I7 -> 124 | K7: =IFERROR(J7/B7,0) -> 0.45925926
A8: Celebration Cake — standard | B8: 95 | C8: =B8*Assumptions!$B$5 -> 26.6 | D8: =Assumptions!$B$9 -> 4 | E8: =Assumptions!$B$14*Assumptions!$B$10 -> 33 | F8: =Assumptions!$B$15 -> 15 | G8: =B8*Assumptions!$B$16 -> 2.85 | H8: =B8*Assumptions!$B$17 -> 0.95 | I8: =SUM(C8:H8) -> 82.4 | J8: =B8-I8 -> 12.6 | K8: =IFERROR(J8/B8,0) -> 0.13263158
A9: Blended average (equal-weighted) | B9: =AVERAGE(B5:B8) -> 181.25 | I9: =AVERAGE(I5:I8) -> 108.35 | J9: =AVERAGE(J5:J8) -> 72.9 | K9: =AVERAGE(K5:K8) -> 0.36202033
A11: Blended average assumes equal order mix across the 4 products — adjust Monthly P&L's Avg Order Value manually if your real mix differs.

Sheet Monthly P&L
A1: Monthly P&L by Volume — Catering & Cakes Division
A2: Three volume scenarios. Avg Order Value defaults to the blended average from Unit Economics — overwrite in blue if your real order mix differs.
A4: Metric | B4: 10 orders/mo | C4: 25 orders/mo | D4: 50 orders/mo
A5: Orders / month | B5: 10 | C5: 25 | D5: 50
A6: Avg order value | B6: ='Unit Economics'!$B$9 -> 181.25 | C6: ='Unit Economics'!$B$9 -> 181.25 | D6: ='Unit Economics'!$B$9 -> 181.25
A7: Revenue | B7: =B5*B6 -> 1812.5 | C7: =C5*C6 -> 4531.25 | D7: =D5*D6 -> 9062.5
A8: Blended gross margin % | B8: ='Unit Economics'!$K$9 -> 0.36202033 | C8: ='Unit Economics'!$K$9 -> 0.36202033 | D8: ='Unit Economics'!$K$9 -> 0.36202033
A9: Gross profit (COGS-adjusted) | B9: =B7*B8 -> 656.16185 | C9: =C7*C8 -> 1640.4046 | D9: =D7*D8 -> 3280.8092
A10: Monthly Google Ads spend | B10: =Assumptions!$B$18 -> 1200 | C10: =Assumptions!$B$18 -> 1200 | D10: =Assumptions!$B$18 -> 1200
A11: Monthly Meta/Instagram Ads spend | B11: =Assumptions!$B$19 -> 600 | C11: =Assumptions!$B$19 -> 600 | D11: =Assumptions!$B$19 -> 600
A12: Other division overhead | B12: =Assumptions!$B$20 -> 0 | C12: =Assumptions!$B$20 -> 0 | D12: =Assumptions!$B$20 -> 0
A13: Distributable profit | B13: =B9-B10-B11-B12 -> -1143.8382 | C13: =C9-C10-C11-C12 -> -159.59539 | D13: =D9-D10-D11-D12 -> 1480.8092
A14: Pau's share (50%) | B14: =B13*Assumptions!$B$21 -> -571.91908 | C14: =C13*Assumptions!$B$21 -> -79.797693 | D14: =D13*Assumptions!$B$21 -> 740.40461
A15: Chef's share (50%) | B15: =B13*Assumptions!$B$22 -> -571.91908 | C15: =C13*Assumptions!$B$22 -> -79.797693 | D15: =D13*Assumptions!$B$22 -> 740.40461
A17: Distributable profit turns negative if ad spend exceeds gross profit at low volume — that's the breakeven signal to watch during the Google Ads validation phase.
